santic_validation/__init__.py
santic_validation/decorator.py
santic_validation/fields.py
santic_validation/utils.py
tests/__init__.py
tests/test_decorator.py
tests/test_fields.py
tests/test_utils.py
santic_validation-0.0.5.dist-info/LICENSE
santic_validation-0.0.5.dist-info/METADATA
santic_validation-0.0.5.dist-info/WHEEL
santic_validation-0.0.5.dist-info/top_level.txt
santic_validation-0.0.5.dist-info/RECORD
