Metadata-Version: 2.1
Name: santic-validation
Version: 0.0.5
Summary: Sanic pydantic validation
Home-page: https://github.com/weiztech/santic-validation
Author: Weiztech
License: MIT
Platform: any
Classifier: Development Status :: 4 - Beta
Classifier: Environment :: Web Environment
Classifier: License :: OSI Approved :: MIT License
Classifier: Programming Language :: Python :: 3.8
Classifier: Programming Language :: Python :: 3.9
Classifier: Programming Language :: Python :: 3.10
License-File: LICENSE
Requires-Dist: pydantic
Requires-Dist: sanic
Provides-Extra: test
Requires-Dist: sanic ; extra == 'test'
Requires-Dist: sanic-testing ; extra == 'test'
Requires-Dist: pydantic ; extra == 'test'
Requires-Dist: pytest ; extra == 'test'
Requires-Dist: pytest-asyncio ; extra == 'test'
Requires-Dist: tox ; extra == 'test'
